bcrg/__init__.py
bcrg/__main__.py
bcrg/font.lua
bcrg/framebuf.lua
bcrg/gui copy.py
bcrg/reticledraw.lua
bcrg/text.py
bcrg-1.2.0.dist-info/licenses/LICENSE
bcrg-1.2.0.dist-info/METADATA
bcrg-1.2.0.dist-info/WHEEL
bcrg-1.2.0.dist-info/entry_points.txt
bcrg-1.2.0.dist-info/top_level.txt
bcrg-1.2.0.dist-info/RECORD
