Metadata-Version: 2.4
Name: bcrg
Version: 1.2.0
Summary: Ballistics reticle generator
Project-URL: Homepage, https://github.com/o-murphy/bcrg
Project-URL: Bug Reports, https://github.com/o-murphy/bcrg/issues
Project-URL: Source, https://github.com/o-murphy/bcrg
Keywords: ballistics,reticles,lua,luascript,python,python3
Classifier: Intended Audience :: Developers
Classifier: Natural Language :: English
Classifier: Programming Language :: Python
Classifier: Topic :: Software Development :: Libraries :: Python Modules
Classifier: Programming Language :: Python :: 3
Classifier: Programming Language :: Python :: 3 :: Only
Classifier: Programming Language :: Python :: 3.7
Classifier: Programming Language :: Python :: 3.8
Classifier: Programming Language :: Python :: 3.9
Classifier: Programming Language :: Python :: 3.10
Classifier: Programming Language :: Python :: 3.11
Classifier: Programming Language :: Python :: 3.12
Classifier: Operating System :: OS Independent
Classifier: Programming Language :: Python :: Implementation :: CPython
Requires-Python: >=3.9
License-File: LICENSE
Requires-Dist: dearpygui>=2.1.0
Requires-Dist: lupa>=2.5
Dynamic: license-file
